[
  {
    "type": "news",
    "position":1,
    "link":"https:\/\/www.zoomerradio.ca\/blogs\/station-blog\/2025\/07\/09\/james-pasternak-discusses-the-troubled-opening-of-rogers-stadium\/",
    "title":"James Pasternak Discusses The Troubled Opening of Rogers Stadium",
    "source":"Zoomer Radio AM740",
    "date":"Jul 9, 2025",
    "published_at":"2025-07-09 07:00:00 UTC",
    "snippet":"City Councillor for the area, James Pasternak, joined The Morning Zoom with Andy & Jane to discuss what those changes were and if they did in fact work.",
    "favicon":"https:\/\/serpapi.com\/searches\/68bce47af8cc7871e438cebe\/images\/b76a5892c18894f24f2a61ed57f861637fadde4398b5b909.png",
    "thumbnail":"https:\/\/serpapi.com\/searches\/68bce47af8cc7871e438cebe\/images\/b76a5892c18894f2a0457aef75b8d61bd0c7b546a4648417074c9f2dd9bf3da9.jpeg"
  },
  {
    "type": "news",
    "position":2,
    "link":"https:\/\/ca.billboard.com\/music\/music-news\/kneecap-toronto-councillor",
    "title":"Toronto City Councillor James Pasternak Calls on Federal Government to Ban Kneecap From Entering the Country",
    "source":"Billboard Canada",
    "date":"1 month ago",
    "published_at":"2025-07-24 07:00:00 UTC",
    "snippet":"On Monday (July 21), Toronto City Councillor James Pasternak called for Irish rap group Kneecap to be banned from entering Canada.",
    "favicon":"https:\/\/serpapi.com\/searches\/68bce47af8cc7871e438cebe\/images\/b76a5892c18894f22858a989f0afe13422dc9067d8fc080a.png",
    "thumbnail":"https:\/\/serpapi.com\/searches\/68bce47af8cc7871e438cebe\/images\/b76a5892c18894f2f43fa3c6e5ee5f4231b2323a7b3a1911509837c522a659fd.jpeg"
  }
]